matplotlive/__init__.py
matplotlive/exceptions.py
matplotlive/live_plot.py
matplotlive/sketch.py
matplotlive-1.1.1.dist-info/LICENSE
matplotlive-1.1.1.dist-info/WHEEL
matplotlive-1.1.1.dist-info/METADATA
matplotlive-1.1.1.dist-info/RECORD
